ratisbona_shellutils/__init__.py
ratisbona_shellutils/calendar/__init__.py
ratisbona_shellutils/calendar/__main__.py
ratisbona_shellutils/calendar/_gitlogging.py
ratisbona_shellutils/calendar/_google_calendar.py
ratisbona_shellutils/calendar/google_calender_cli.py
ratisbona_shellutils/dialogator/__init__.py
ratisbona_shellutils/dialogator/__main__.py
ratisbona_shellutils/dialogator/chatgpt_parsing.py
ratisbona_shellutils/dialogator/dialogator.py
ratisbona_shellutils/dialogator/dialogator_cli.py
ratisbona_shellutils/dialogator/teams_parsing.py
ratisbona_shellutils/dialogator/test.py
ratisbona_shellutils/dialogator/whatsapp_zip_parsing.py
ratisbona_shellutils/emojifind/__init__.py
ratisbona_shellutils/emojifind/__main__.py
ratisbona_shellutils/emojifind/_emojifind.py
ratisbona_shellutils/emojifind/_emojifind_cli.py
ratisbona_shellutils/emojifind/resources/__init__.py
ratisbona_shellutils/emojifind/resources/additional_emojis.json
ratisbona_shellutils/file_organisation/__init__.py
ratisbona_shellutils/file_organisation/__main__.py
ratisbona_shellutils/file_organisation/_fileorga_cli.py
ratisbona_shellutils/labeldisks/__init__.py
ratisbona_shellutils/labeldisks/__main__.py
ratisbona_shellutils/labeldisks/_labeldisks.py
ratisbona_shellutils/labeldisks/labeldisks_cli.py
ratisbona_shellutils/latex/__init__.py
ratisbona_shellutils/latex/__main__.py
ratisbona_shellutils/latex/_latex.py
ratisbona_shellutils/latex/resources/__init__.py
ratisbona_shellutils/latex/resources/labeldoc.cls
ratisbona_shellutils/length_encode/__init__.py
ratisbona_shellutils/length_encode/__main__.py
ratisbona_shellutils/length_encode/_length_encode.py
ratisbona_shellutils/length_encode/_length_encode_cli.py
ratisbona_shellutils/messysoft/__init__.py
ratisbona_shellutils/messysoft/__main__.py
ratisbona_shellutils/messysoft/_messysoft.py
ratisbona_shellutils/messysoft/_messysoft_chats.py
ratisbona_shellutils/messysoft/_messysoft_cli.py
ratisbona_shellutils/messysoft/_messysoft_mail.py
ratisbona_shellutils-0.0.4.dist-info/METADATA
ratisbona_shellutils-0.0.4.dist-info/WHEEL
ratisbona_shellutils-0.0.4.dist-info/entry_points.txt
ratisbona_shellutils-0.0.4.dist-info/licenses/LICENSE
ratisbona_shellutils-0.0.4.dist-info/RECORD
