Metadata-Version: 2.4
Name: ratisbona_shellutils
Version: 0.0.4
Summary: A python package comprising a collection of shell utilities, such as: ratisbona_gcalendar, a command line interface that can sync git logs and other stuff to google calendar, ratisbona_dialogator, a set of tools revolving around the so called dialoge markdown useful for archiving and typesetting whatsapp conversations or chat-gpt dialogs. ratisbona_paste_image, a utility that can be very useful for example for copy and pasting images into VI.
Project-URL: Homepage, https://github.com/pypa/sampleproject
Project-URL: Bug Tracker, https://github.com/pypa/sampleproject/issues
Author-email: Ulrich Schwenk <ulrich.schwenk@gmail.com>
License-File: LICENSE
Classifier: License :: OSI Approved :: GNU General Public License v2 (GPLv2)
Classifier: Operating System :: OS Independent
Classifier: Programming Language :: Python :: 3
Requires-Python: >=3.10
Requires-Dist: click
Requires-Dist: emoji
Requires-Dist: gitpython
Requires-Dist: google-api-python-client
Requires-Dist: google-auth
Requires-Dist: google-auth-oauthlib
Requires-Dist: html2text
Requires-Dist: markdown-it-py
Requires-Dist: mdit-py-plugins
Requires-Dist: more-itertools
Requires-Dist: msal
Requires-Dist: pathlib
Requires-Dist: pyautogui
Requires-Dist: pynput
Requires-Dist: pyqt5
Requires-Dist: ratisbona-utils>=0.0.4
Requires-Dist: transliterate
Requires-Dist: unidecode
Provides-Extra: dev
Requires-Dist: black; extra == 'dev'
Requires-Dist: black[d]; extra == 'dev'
Requires-Dist: build; extra == 'dev'
Requires-Dist: coverage; extra == 'dev'
Requires-Dist: mypy; extra == 'dev'
Requires-Dist: poethepoet; extra == 'dev'
Requires-Dist: pylint; extra == 'dev'
Requires-Dist: twine; extra == 'dev'
